cueman/__init__.py
cueman/__main__.py
cueman/main.py
opencue_cueman-1.13.8.dist-info/METADATA
opencue_cueman-1.13.8.dist-info/WHEEL
opencue_cueman-1.13.8.dist-info/entry_points.txt
opencue_cueman-1.13.8.dist-info/RECORD
