Metadata-Version: 2.1
Name: opencue_cueman
Version: 1.13.8
Summary: Cueman is a command-line job management tool for OpenCue that provides efficient job control operations. It offers a streamlined interface for managing jobs, frames, and processes with advanced filtering and batch operation capabilities.
Requires-Python: >3.7
Requires-Dist: opencue-cueadmin
Requires-Dist: opencue-pycue
Provides-Extra: dev
Requires-Dist: black; extra == 'dev'
Requires-Dist: isort; extra == 'dev'
Requires-Dist: mock==2.0.0; extra == 'dev'
Requires-Dist: pyfakefs==5.2.3; extra == 'dev'
Requires-Dist: pylint; extra == 'dev'
Requires-Dist: pytest; extra == 'dev'
Requires-Dist: pytest-cov; extra == 'dev'
Requires-Dist: pytest-mock; extra == 'dev'
Provides-Extra: test
Requires-Dist: mock==2.0.0; extra == 'test'
Requires-Dist: pyfakefs==5.2.3; extra == 'test'
Requires-Dist: pytest; extra == 'test'
Requires-Dist: pytest-cov; extra == 'test'
Requires-Dist: pytest-mock; extra == 'test'
